MANIFEST.in
setup.cfg
setup.py
examples/interactive_client/README.md
examples/interactive_client/console.py
examples/interactive_client/contacts_api
examples/interactive_client/method_caller.py
examples/interactive_client/oauth.py
examples/interactive_client/reflection.py
examples/interactive_client/settings.py
examples/interactive_client/verbose_api.py
shuttlecloud/__init__.py
shuttlecloud.contacts_api_client.egg-info/PKG-INFO
shuttlecloud.contacts_api_client.egg-info/SOURCES.txt
shuttlecloud.contacts_api_client.egg-info/dependency_links.txt
shuttlecloud.contacts_api_client.egg-info/namespace_packages.txt
shuttlecloud.contacts_api_client.egg-info/not-zip-safe
shuttlecloud.contacts_api_client.egg-info/requires.txt
shuttlecloud.contacts_api_client.egg-info/top_level.txt
shuttlecloud/contacts_api_client/__init__.py
shuttlecloud/contacts_api_client/client.py