Metadata-Version: 1.1
Name: shuttlecloud.contacts-api-client
Version: 0.0.10
Summary: ShuttleCloud Contacts API Official Python Client
Home-page: http://github.com/shuttlecloud/contacts-api-client
Author: ShuttleCloud Corp.
Author-email: dev@shuttlecloud.com
License: UNKNOWN
Platform: UNKNOWN
Classifier: Development Status :: 4 - Beta
Classifier: Environment :: Console
Classifier: Intended Audience :: Developers
Classifier: License :: OSI Approved :: GNU General Public License v3 or later (GPLv3+)
Classifier: Programming Language :: Python :: 2
